mass2chem/__init__.py
mass2chem/formula.py
mass2chem/io.py
mass2chem/search.py
mass2chem/identifiers/__init__.py
mass2chem/lib/LCMS_contaminants.py
mass2chem/lib/__init__.py
mass2chem/lib/common_mass.py
mass2chem/lib/contaminants.py
mass2chem/lib/formula_coordinate.py
mass2chem/lib/ions_contaminants.py
mass2chem/lib/mzdiff_bioreaction.py
mass2chem/lib/mzdiff_in_source.py
mass2chem/lib/reaction_rules.py
mass2chem/source_data/NIST_isotope_data.py
mass2chem/source_data/__init__.py
mass2chem-0.5.0.dist-info/LICENSE
mass2chem-0.5.0.dist-info/METADATA
mass2chem-0.5.0.dist-info/WHEEL
mass2chem-0.5.0.dist-info/top_level.txt
mass2chem-0.5.0.dist-info/RECORD
