Metadata-Version: 2.1
Name: mass2chem
Version: 0.5.0
Summary: Common utilities for interpreting mass spectrometry data
Home-page: https://github.com/shuzhao-li/mass2chem
Author: Shuzhao Li
Author-email: shuzhao.li@gmail.com
License: BSD
Keywords: chemistry,bioinformatics,mass spectrometry
Classifier: Development Status :: 4 - Beta
Classifier: Intended Audience :: Developers
Classifier: Intended Audience :: Science/Research
Classifier: License :: OSI Approved :: BSD License
Classifier: Natural Language :: English
Classifier: Operating System :: OS Independent
Classifier: Programming Language :: Python :: 3.7
Classifier: Topic :: Scientific/Engineering :: Bio-Informatics
Classifier: Topic :: Software Development :: Libraries :: Python Modules
Requires-Python: >=3.7
License-File: LICENSE
Requires-Dist: numpy
Requires-Dist: scipy
